setup.py
printjoke/__init__.py
printjoke.egg-info/PKG-INFO
printjoke.egg-info/SOURCES.txt
printjoke.egg-info/dependency_links.txt
printjoke.egg-info/not-zip-safe
printjoke.egg-info/top_level.txt