Metadata-Version: 1.0
Name: printjoke
Version: 0.3
Summary: print no jkoke
Home-page: UNKNOWN
Author: joker
Author-email: joker@gmail.com
License: MIT
Platform: UNKNOWN
